{
  "file": "data/datos-tecnicos/DADOS TÉCNICOS E TORQUES/Motores Pesados/Volvo/FL 6.pdf",
  "file_hash": "51a42b6283f3b52b",
  "title": "FL 6",
  "pages": 5,
  "category": "technical_specs",
  "system": "engine",
  "dtcs_mentioned": [],
  "vehicles_mentioned": [
    {
      "make": "Volvo",
      "model": "",
      "year_range": ""
    }
  ],
  "ecus_mentioned": [],
  "tools_required": [],
  "pin_numbers_seen": [],
  "procedures": [],
  "torque_specs": [],
  "summary_es": "Vehiculos: Volvo | Sistema: engine",
  "error": ""
}