{
  "file": "data/localizacion-componentes/LOCALIZAÇÃO DE COMPONENTES/VW/Golf 1.6 - 1.8 - 2.0 de 2001 em diante.pdf",
  "file_hash": "f6733c1ce4d3c89c",
  "title": "Golf 1.6 - 1.8 - 2.0 de 2001 em diante",
  "pages": 5,
  "category": "component_location",
  "system": "unknown",
  "dtcs_mentioned": [],
  "vehicles_mentioned": [
    {
      "make": "VW",
      "model": "",
      "year_range": ""
    }
  ],
  "ecus_mentioned": [],
  "tools_required": [],
  "pin_numbers_seen": [],
  "procedures": [],
  "torque_specs": [],
  "summary_es": "Vehiculos: VW | Sistema: unknown",
  "error": ""
}